{
  "carrental": {
    "pLocation": "//span[contains(@id,'select2-pickup_location')]",
    "pLocationField": "//*[contains(@aria-controls,'select2-pickup_location')]",
    "chkBoxSameLocation": "//label[@class='label_chkbox']",
    "rLocation": "//span[contains(@id,'select2-dropoff_location')]",
    "rLocationField" : "//*[contains(@aria-controls,'select2-dropoff_location')]",
    "sDate": ".js-datepicker-start",
    "eDate": ".js-datepicker-end",
    "sTime": "//*[contains(@id,'select2-start_time')]",
    "eTime": "//*[contains(@id,'select2-end_time')]",
    "chkBoxCountryAge": "//label[@class='js-extra-info label_chkbox']",
    "country": "//span[contains(@id, 'select2-country')]",
    "countryField": "//*[contains(@aria-controls,'select2-country')]",
    "age": "*[name='age']",
    "btnSubmit": "//div[@class='section-submit']/button",
    "ddlResult": "[class='select2-results__options'][role='listbox'] li",
    "dtPickerMonthView": "(//th[@class='datepicker-switch'])[1]",
    "dtPickerYearView": "(//th[@class='datepicker-switch'])[2]",
    "dtPickerDecadeView": "(//th[@class='datepicker-switch'])[3]",
    "dtPickerNextDecade": "(//th[@class='next'])[3]",
    "dtPickerPrevDecade": "(//th[@class='prev'])[3]",
    "chkBoxSuggested": "//*[@data-key='suggested']//div[contains(@class,'pull-left')]/span",
    "chkBoxNumOfPeople": "//*[@data-key='people']//div[contains(@class,'pull-left')]/span",
    "chkBoxLocationType": "//*[@data-key='locationtype']//div[contains(@class,'pull-left')]/span",
    "chkBoxTransmission": "//*[@data-key='transmission']//div[contains(@class,'pull-left')]/span",
    "chkBoxCarType": "//*[@data-key='categoryid']//div[contains(@class,'pull-left')]/span",
    "chkBoxRentalCompany": "//*[@data-key='companyid']//div[contains(@class,'pull-left')]/span",
    "chkBoxDamageExcess": "//*[@data-key='excess']//div[contains(@class,'pull-left')]/span",
    "chkBoxPaymentType": "//*[@data-key='paymenttype']//div[contains(@class,'pull-left')]/span",
    "carResults": "//ul[@class='resultsGroup']/li",
    "totalCars": ".js-total",
    "next": ".js-prevNext[aria-label='Next']",
    "prev": ".js-prevNext[aria-label='Previous']",
    "avgCarPrice": ".price-desc"
  },
  "demoqa": {}
}
